<templateSet group="Flutter">
  <template name="mqow" value="MediaQuery.of(context).size.width" description="To get the screen width" toReformat="false" toShortenFQNames="true">
    <context>
      <option name="DART" value="true" />
    </context>
  </template>
  <template name="mqoh" value="MediaQuery.of(context).size.height" description="To get the height of the screen" toReformat="false" toShortenFQNames="true">
    <context>
      <option name="DART" value="true" />
    </context>
  </template>
  <template name="gxv" value="class $PAGE_NAME$Page&#10;    extends GetView&lt;$PAGE_NAME$PageController&gt; {&#10; @override&#10;  Widget build(BuildContext context) {&#10;    return Container($END$);&#10;  }&#10;}&#10;class $PAGE_NAME$PageController extends GetxController {}&#10;" description="" toReformat="false" toShortenFQNames="true">
    <variable name="PAGE_NAME" expression="" defaultValue="" alwaysStopAt="true" />
    <context>
      <option name="DART_TOPLEVEL" value="true" />
    </context>
  </template>
  <template name="gxvwb" value="class $NAME$Page extends GetView&lt;$NAME$PageController&gt; {&#10;  @override&#10;  Widget build(BuildContext context) {&#10;    return GetBuilder&lt;$NAME$PageController&gt;(&#10;     builder: (value) =&gt; Scaffold(&#10;        body: Container($END$),&#10;      ),&#10;    );&#10;  }&#10;}&#10;&#10;class $NAME$PageController extends GetxController {}&#10;" description="" toReformat="false" toShortenFQNames="true">
    <variable name="NAME" expression="" defaultValue="" alwaysStopAt="true" />
    <context>
      <option name="DART_TOPLEVEL" value="true" />
    </context>
  </template>
  <template name="gxcon" value="class $NAME$PageController extends GetxController {&#10;    $END$&#10;}" description="" toReformat="false" toShortenFQNames="true">
    <variable name="NAME" expression="" defaultValue="" alwaysStopAt="true" />
    <context>
      <option name="DART_TOPLEVEL" value="true" />
    </context>
  </template>
  <template name="gxlzput" value="Get.lazyPut&lt;$CONTROLLER_NAME$&gt;(&#10;    () =&gt; $CONTROLLER_NAME$(),&#10;    fenix: true,&#10;);" description="" toReformat="false" toShortenFQNames="true">
    <variable name="CONTROLLER_NAME" expression="" defaultValue="" alwaysStopAt="true" />
    <context>
      <option name="DART" value="true" />
      <option name="DART_TOPLEVEL" value="false" />
    </context>
  </template>
  <template name="gxbind" value="class $BUNDING_NAME$ implements Bindings {&#10;  @override&#10;  void dependencies() {&#10;    // TODO: implement dependencies&#10;  }&#10;}" description="" toReformat="false" toShortenFQNames="true">
    <variable name="BUNDING_NAME" expression="" defaultValue="" alwaysStopAt="true" />
    <context>
      <option name="DART_TOPLEVEL" value="true" />
    </context>
  </template>
</templateSet>